_pynetworktables/__init__.py
_pynetworktables/entry.py
_pynetworktables/instance.py
_pynetworktables/py.typed
_pynetworktables/table.py
_pynetworktables/_impl/__init__.py
_pynetworktables/_impl/api.py
_pynetworktables/_impl/callback_manager.py
_pynetworktables/_impl/connection_notifier.py
_pynetworktables/_impl/constants.py
_pynetworktables/_impl/dispatcher.py
_pynetworktables/_impl/ds_client.py
_pynetworktables/_impl/entry_notifier.py
_pynetworktables/_impl/message.py
_pynetworktables/_impl/network_connection.py
_pynetworktables/_impl/rpc_server.py
_pynetworktables/_impl/storage.py
_pynetworktables/_impl/storage_load.py
_pynetworktables/_impl/storage_save.py
_pynetworktables/_impl/structs.py
_pynetworktables/_impl/value.py
_pynetworktables/_impl/version.py
_pynetworktables/_impl/wire.py
_pynetworktables/_impl/support/__init__.py
_pynetworktables/_impl/support/_impl.py
_pynetworktables/_impl/support/_impl_debug.py
_pynetworktables/_impl/support/leb128.py
_pynetworktables/_impl/support/lists.py
_pynetworktables/_impl/support/safe_thread.py
_pynetworktables/_impl/support/uidvector.py
_pynetworktables/_impl/tcpsockets/__init__.py
_pynetworktables/_impl/tcpsockets/tcp_acceptor.py
_pynetworktables/_impl/tcpsockets/tcp_connector.py
_pynetworktables/_impl/tcpsockets/tcp_stream.py
networktables/__init__.py
networktables/__init__.pyi
networktables/entry.py
networktables/networktable.py
networktables/py.typed
networktables/util.py
pynetworktables-2020.0.4.dist-info/LICENSE.txt
pynetworktables-2020.0.4.dist-info/METADATA
pynetworktables-2020.0.4.dist-info/WHEEL
pynetworktables-2020.0.4.dist-info/top_level.txt
pynetworktables-2020.0.4.dist-info/RECORD
