Metadata-Version: 1.2
Name: pynetworktables
Version: 2020.0.4
Summary: A pure Python implementation of NetworkTables, used for robot communications in the FIRST Robotics Competition.
Home-page: https://github.com/robotpy/pynetworktables
Author: Dustin Spicuzza, Peter Johnson
Author-email: robotpy@googlegroups.com
License: BSD-3-Clause
Keywords: frc first robotics wpilib networktables
Platform: UNKNOWN
Classifier: Development Status :: 5 - Production/Stable
Classifier: Intended Audience :: Developers
Classifier: Intended Audience :: Education
Classifier: License :: OSI Approved :: BSD License
Classifier: Operating System :: OS Independent
Classifier: Programming Language :: Python :: 3
Classifier: Programming Language :: Python :: 3.5
Classifier: Programming Language :: Python :: 3.6
Classifier: Programming Language :: Python :: 3.7
Classifier: Programming Language :: Python :: 3.8
Classifier: Topic :: Scientific/Engineering
Requires-Python: >=3.5
